Wheelhouse-0.1.4.dist-info/DESCRIPTION.rst
Wheelhouse-0.1.4.dist-info/METADATA
Wheelhouse-0.1.4.dist-info/RECORD
Wheelhouse-0.1.4.dist-info/WHEEL
Wheelhouse-0.1.4.dist-info/entry_points.txt
Wheelhouse-0.1.4.dist-info/metadata.json
Wheelhouse-0.1.4.dist-info/top_level.txt
wheelhouse/__init__.py
wheelhouse/appdirs.py
wheelhouse/cli.py
wheelhouse/config.py
wheelhouse/core.py
wheelhouse/version.py
