Metadata-Version: 2.0
Name: Wheelhouse
Version: 0.1.4
Summary: A utility to help maintain a wheelhouse.
Home-page: https://github.com/level12/wheelhouse
Author: Randy Syring
Author-email: randy.syring@level12.io
License: BSD
Platform: UNKNOWN
Classifier: Development Status :: 4 - Beta
Classifier: Intended Audience :: Developers
Classifier: License :: OSI Approved :: BSD License
Classifier: Operating System :: OS Independent
Classifier: Programming Language :: Python :: 2
Classifier: Programming Language :: Python :: 2.7
Classifier: Programming Language :: Python :: 3
Classifier: Programming Language :: Python :: 3.3
Classifier: Programming Language :: Python :: 3.4
Requires-Dist: pip
Requires-Dist: wheel
Requires-Dist: click
Requires-Dist: pathlib
